easshy/__init__.py
easshy/easshy.py
easshy-0.0.1.dist-info/METADATA
easshy-0.0.1.dist-info/WHEEL
easshy-0.0.1.dist-info/entry_points.txt
easshy-0.0.1.dist-info/top_level.txt
easshy-0.0.1.dist-info/RECORD
