Metadata-Version: 2.1
Name: easshy
Version: 0.0.1
Summary: A simple tool that lets you easily manage your SSH servers credentials.
Home-page: https://github.com/Fastiraz/easshy
Author: Fastiraz
Author-email: 
Maintainer: Fastiraz
Project-URL: Homepage, https://github.com/Fastiraz/easshy
Project-URL: Issues, https://github.com/Fastiraz/easshy/issues
Keywords: ssh,credential,manager,cryptography
Classifier: Programming Language :: Python :: 3
Classifier: Development Status :: 2 - Pre-Alpha
Classifier: Topic :: Security :: Cryptography
Classifier: Environment :: Console
Classifier: Operating System :: POSIX :: Linux
Classifier: Operating System :: Unix
Classifier: Operating System :: MacOS
Classifier: Programming Language :: Python :: 3
Requires-Python: >=3.10
Requires-Dist: keyboard
Requires-Dist: cryptography
